MANIFEST.in
README.md
exacttarget.py
setup.py
python_exacttarget.egg-info/PKG-INFO
python_exacttarget.egg-info/SOURCES.txt
python_exacttarget.egg-info/dependency_links.txt
python_exacttarget.egg-info/top_level.txt